setup.py
unicorn_8642_fu/__init__.py
unicorn_8642_fu/one.py
unicorn_8642_fu/two.py
unicorn_8642_fu.egg-info/PKG-INFO
unicorn_8642_fu.egg-info/SOURCES.txt
unicorn_8642_fu.egg-info/dependency_links.txt
unicorn_8642_fu.egg-info/top_level.txt